NoetherAutoDiff/NoetherAD.py
NoetherAutoDiff/NoetherADPy.so
NoetherAutoDiff/__init__.py
NoetherAutoDiff/libNoetherAutoDiff.dylib
NoetherAutoDiff-1.0.0.dist-info/DESCRIPTION.rst
NoetherAutoDiff-1.0.0.dist-info/METADATA
NoetherAutoDiff-1.0.0.dist-info/RECORD
NoetherAutoDiff-1.0.0.dist-info/WHEEL
NoetherAutoDiff-1.0.0.dist-info/metadata.json
NoetherAutoDiff-1.0.0.dist-info/top_level.txt
