Metadata-Version: 2.0
Name: NoetherAutoDiff
Version: 1.0.0
Summary: A Python wrapper for an efficient C++ library that is used for Auto Differentiation
Home-page: https://github.com/cs107-noether/cs107-FinalProject
Author: Sam Negassi
Author-email: samson.s.negassi@gmail.com
License: MIT
Download-URL: https://github.com/cs107-noether/cs107-FinalProject/archive/v0.1.tar.gz
Keywords: Auto,Differentiation,AutoDiff,Jacobian,Derivation
Platform: UNKNOWN
Classifier: Development Status :: 3 - Alpha
Classifier: Intended Audience :: Developers
Classifier: Topic :: Software Development :: Build Tools
Classifier: License :: OSI Approved :: MIT License
Classifier: Programming Language :: Python :: 3
Classifier: Programming Language :: Python :: 3.4
Classifier: Programming Language :: Python :: 3.5
Classifier: Programming Language :: Python :: 3.6
